__init__.py
arcoder.py
arcoder-0.1.0.dist-info/LICENSE.md
arcoder-0.1.0.dist-info/METADATA
arcoder-0.1.0.dist-info/WHEEL
arcoder-0.1.0.dist-info/top_level.txt
arcoder-0.1.0.dist-info/RECORD
