Metadata-Version: 2.1
Name: arcoder
Version: 0.1.0
Summary: Implementation of the ARCoder Transliterated Arabic Name Matching Encoding Algorithm
Author: Seth Bromberger, Jessica Moore, Sam Hamid
License: MIT
Keywords: name matching,Arabic
Classifier: Programming Language :: Python :: 3
Classifier: Operating System :: OS Independent
Requires-Python: >=3.9
License-File: LICENSE.md
